text_image_generator-0.2.6.dist-info/METADATA
text_image_generator-0.2.6.dist-info/WHEEL
text_image_generator/__init__.py
text_image_generator/__init__.pyi
text_image_generator/py.typed
text_image_generator/text_image_generator.pypy310-pp73-x86-linux-gnu.so
text_image_generator-0.2.6.dist-info/RECORD
